LICENSE
MANIFEST.in
README.rst
requirements.txt
setup.py
terraform_provider_freebox/__init__.py
terraform_provider_freebox.egg-info/PKG-INFO
terraform_provider_freebox.egg-info/SOURCES.txt
terraform_provider_freebox.egg-info/dependency_links.txt
terraform_provider_freebox.egg-info/entry_points.txt
terraform_provider_freebox.egg-info/requires.txt
terraform_provider_freebox.egg-info/top_level.txt