Metadata-Version: 1.1
Name: terraform-provider-freebox
Version: 0.0.2
Summary: Terraform provider to configure Freebox xDSL/FTTH modems
Home-page: http://jacquev6.github.io/terraform-provider-freebox
Author: Vincent Jacques
Author-email: vincent@vincent-jacques.net
License: MIT
Platform: UNKNOWN
Classifier: Development Status :: 3 - Alpha
Classifier: License :: OSI Approved
Classifier: License :: OSI Approved :: MIT License
Classifier: Operating System :: OS Independent
Classifier: Programming Language :: Python
Classifier: Programming Language :: Python :: 3
